{
    "NAME": "ch130",
    "TYPE": "TSP",
    "COMMENT": "130 city problem (Churritz)",
    "DIMENSION": "130",
    "EDGE_WEIGHT_TYPE": "EUC_2D",
    "NODE_COORD_SECTION": [
        [
            1.0,
            334.5909245845,
            161.7809319139
        ],
        [
            2.0,
            397.6446634067,
            262.8165330708
        ],
        [
            3.0,
            503.8741827107,
            172.8741151168
        ],
        [
            4.0,
            444.0479403502,
            384.6491809647
        ],
        [
            5.0,
            311.6137146746,
            2.0091699828
        ],
        [
            6.0,
            662.8551011379,
            549.2301263653
        ],
        [
            7.0,
            40.0979030612,
            187.2375430791
        ],
        [
            8.0,
            526.8941409181,
            215.7079092185
        ],
        [
            9.0,
            209.1887938487,
            691.0262291948
        ],
        [
            10.0,
            683.2674131973,
            414.2096286906
        ],
        [
            11.0,
            280.7494438748,
            5.9206392047
        ],
        [
            12.0,
            252.749309008,
            535.7430385019
        ],
        [
            13.0,
            698.7850451923,
            348.4413729766
        ],
        [
            14.0,
            678.7574678104,
            410.7256424438
        ],
        [
            15.0,
            220.0041131179,
            409.1225812873
        ],
        [
            16.0,
            355.1528556851,
            76.3912076444
        ],
        [
            17.0,
            296.9724227786,
            313.1312792361
        ],
        [
            18.0,
            504.5154071733,
            240.8866564499
        ],
        [
            19.0,
            224.1079496785,
            358.4872228907
        ],
        [
            20.0,
            470.6801296968,
            309.6259188406
        ],
        [
            21.0,
            554.2530513223,
            279.4242466521
        ],
        [
            22.0,
            567.6332684419,
            352.7162027273
        ],
        [
            23.0,
            599.0532671093,
            361.0948690386
        ],
        [
            24.0,
            240.5232959211,
            430.6036007844
        ],
        [
            25.0,
            32.0825972787,
            345.8551009775
        ],
        [
            26.0,
            91.0538736891,
            148.7213270256
        ],
        [
            27.0,
            248.2179894723,
            343.9528017384
        ],
        [
            28.0,
            488.8909044347,
            3.6122311393
        ],
        [
            29.0,
            206.046793982,
            437.7639406167
        ],
        [
            30.0,
            575.8409415632,
            141.9670960195
        ],
        [
            31.0,
            282.6089948164,
            329.4183805862
        ],
        [
            32.0,
            27.6581484868,
            424.7684581747
        ],
        [
            33.0,
            568.573730987,
            287.0975660546
        ],
        [
            34.0,
            269.4638933331,
            295.9464636385
        ],
        [
            35.0,
            417.8004856811,
            341.2596589955
        ],
        [
            36.0,
            32.1680938737,
            448.8998721172
        ],
        [
            37.0,
            561.4775136009,
            357.3543930067
        ],
        [
            38.0,
            342.948216747,
            492.3321423839
        ],
        [
            39.0,
            399.6752075383,
            156.8435035519
        ],
        [
            40.0,
            571.7371050025,
            375.7575350833
        ],
        [
            41.0,
            370.7559842751,
            151.9060751898
        ],
        [
            42.0,
            509.7093253204,
            435.7975189314
        ],
        [
            43.0,
            177.020699975,
            295.6044772584
        ],
        [
            44.0,
            526.1674198605,
            409.4859418161
        ],
        [
            45.0,
            316.5725171854,
            65.6400108214
        ],
        [
            46.0,
            469.2908100279,
            281.9891445025
        ],
        [
            47.0,
            572.7630641427,
            373.3208821255
        ],
        [
            48.0,
            29.5176994283,
            330.0382309
        ],
        [
            49.0,
            454.0082936692,
            537.2178547659
        ],
        [
            50.0,
            416.1546762271,
            227.6133100741
        ],
        [
            51.0,
            535.2514330806,
            471.0648643744
        ],
        [
            52.0,
            265.4455533675,
            684.9987192464
        ],
        [
            53.0,
            478.0542110167,
            509.6452028741
        ],
        [
            54.0,
            370.4781203413,
            332.5390063041
        ],
        [
            55.0,
            598.3479202004,
            446.8693279856
        ],
        [
            56.0,
            201.1521139175,
            649.0260268945
        ],
        [
            57.0,
            193.6925360026,
            680.2322840744
        ],
        [
            58.0,
            448.5792598859,
            532.793405974
        ],
        [
            59.0,
            603.2853485624,
            134.4006473609
        ],
        [
            60.0,
            543.0102490781,
            481.5168231148
        ],
        [
            61.0,
            214.5750793346,
            43.6460117543
        ],
        [
            62.0,
            426.3501451825,
            61.7285415996
        ],
        [
            63.0,
            89.0447037063,
            277.1158385868
        ],
        [
            64.0,
            84.4920100219,
            31.8474816424
        ],
        [
            65.0,
            220.0468614154,
            623.077810308
        ],
        [
            66.0,
            688.4613313444,
            0.4702312726
        ],
        [
            67.0,
            687.285753163,
            373.534623613
        ],
        [
            68.0,
            75.4934933967,
            312.9175377486
        ],
        [
            69.0,
            63.4170993511,
            23.7039309674
        ],
        [
            70.0,
            97.9363495877,
            211.0910930878
        ],
        [
            71.0,
            399.525588497,
            170.8221968365
        ],
        [
            72.0,
            456.3167017346,
            597.1937161677
        ],
        [
            73.0,
            319.8855102422,
            626.8396604886
        ],
        [
            74.0,
            295.9250894897,
            664.6291554845
        ],
        [
            75.0,
            288.4868857235,
            667.7284070537
        ],
        [
            76.0,
            268.3951858954,
            52.9010181645
        ],
        [
            77.0,
            140.4709056068,
            513.556672096
        ],
        [
            78.0,
            689.8079027159,
            167.5947003748
        ],
        [
            79.0,
            280.5784506848,
            458.7533546925
        ],
        [
            80.0,
            453.3884433554,
            282.9082328989
        ],
        [
            81.0,
            213.5704943432,
            525.8681817779
        ],
        [
            82.0,
            133.695300452,
            677.1757808026
        ],
        [
            83.0,
            521.1658690522,
            132.8617086506
        ],
        [
            84.0,
            30.2657946347,
            450.0754502986
        ],
        [
            85.0,
            657.0199585283,
            39.7772908299
        ],
        [
            86.0,
            6.9252241961,
            23.8749241575
        ],
        [
            87.0,
            252.4286967767,
            535.1659364856
        ],
        [
            88.0,
            42.8551682504,
            63.8232081774
        ],
        [
            89.0,
            145.8999393902,
            399.525588497
        ],
        [
            90.0,
            638.4885715591,
            62.6262558472
        ],
        [
            91.0,
            489.2756391122,
            665.3131282446
        ],
        [
            92.0,
            361.2231139311,
            564.2347787901
        ],
        [
            93.0,
            519.9475425732,
            347.971141704
        ],
        [
            94.0,
            129.3349741063,
            435.6692740389
        ],
        [
            95.0,
            259.7172815016,
            454.6495181318
        ],
        [
            96.0,
            676.3421890013,
            371.0979706551
        ],
        [
            97.0,
            84.5133841706,
            183.3260738572
        ],
        [
            98.0,
            77.7164048671,
            354.38338633
        ],
        [
            99.0,
            335.9802442534,
            660.6321896676
        ],
        [
            100.0,
            264.355471781,
            377.5743377274
        ],
        [
            101.0,
            51.6826916855,
            676.0429509187
        ],
        [
            102.0,
            692.13768493,
            543.8010925819
        ],
        [
            103.0,
            169.21913568,
            547.8194325476
        ],
        [
            104.0,
            194.0131482339,
            263.4791316822
        ],
        [
            105.0,
            415.1928395332,
            78.9133571973
        ],
        [
            106.0,
            415.0432204919,
            479.0801701569
        ],
        [
            107.0,
            169.8389859939,
            245.6103433244
        ],
        [
            108.0,
            525.0987124228,
            213.5063718969
        ],
        [
            109.0,
            238.6851191283,
            33.4932910965
        ],
        [
            110.0,
            116.2112467718,
            363.574270294
        ],
        [
            111.0,
            16.9283258126,
            656.5711014044
        ],
        [
            112.0,
            434.3440768162,
            92.6996831431
        ],
        [
            113.0,
            40.5253860363,
            424.6829615797
        ],
        [
            114.0,
            530.4849979086,
            183.8390534273
        ],
        [
            115.0,
            484.359584899,
            49.2460387276
        ],
        [
            116.0,
            263.6501248722,
            426.5852608187
        ],
        [
            117.0,
            450.2891917862,
            126.3853415784
        ],
        [
            118.0,
            441.7822805823,
            299.7724362653
        ],
        [
            119.0,
            24.2169105375,
            500.3474481664
        ],
        [
            120.0,
            503.7886861157,
            514.6895019799
        ],
        [
            121.0,
            635.5389390312,
            200.9811207275
        ],
        [
            122.0,
            614.5922732529,
            418.8691931188
        ],
        [
            123.0,
            21.7161351334,
            660.9741760476
        ],
        [
            124.0,
            143.8266469611,
            92.6996831431
        ],
        [
            125.0,
            637.719102204,
            54.2048412384
        ],
        [
            126.0,
            566.5645610042,
            199.9551615873
        ],
        [
            127.0,
            196.684916828,
            221.8209157619
        ],
        [
            128.0,
            384.9270448985,
            87.4630166986
        ],
        [
            129.0,
            178.1107815614,
            104.6905805938
        ],
        [
            130.0,
            403.2874386776,
            205.8971749407
        ]
    ]
}